zaim_pay_importer/__init__.py
zaim_pay_importer/zaim_pay_importer.py
zaim_pay_importer-1.0.0.dist-info/LICENSE.txt
zaim_pay_importer-1.0.0.dist-info/METADATA
zaim_pay_importer-1.0.0.dist-info/WHEEL
zaim_pay_importer-1.0.0.dist-info/top_level.txt
zaim_pay_importer-1.0.0.dist-info/RECORD
