Metadata-Version: 2.1
Name: zaim-pay-importer
Version: 1.0.0
Summary: zaimに対応していないANA Payや楽天Payの明細をGmailから取得してzaimにインポートするPythonライブラリ
Author-email: tra <tisk0711ngm@gmail.com>
Maintainer-email: tra <tisk0711ngm@gmail.com>
License: MIT License
Project-URL: Source, https://github.com/clcl777/zaim-pay-importer
Classifier: Development Status :: 5 - Production/Stable
Classifier: Intended Audience :: Developers
Classifier: Programming Language :: Python :: 3
Classifier: Environment :: Web Environment
Classifier: License :: OSI Approved :: MIT License
Classifier: Operating System :: OS Independent
Classifier: Typing :: Typed
Classifier: Topic :: Software Development
Requires-Python: >=3.8
License-File: LICENSE.txt
Requires-Dist: PyGmailScraper >=1.1.1
Requires-Dist: zaim-sdk >=0.0.0
Provides-Extra: dev
Requires-Dist: build ; extra == 'dev'
Requires-Dist: twine ; extra == 'dev'
Requires-Dist: types-python-dateutil ; extra == 'dev'
